README.md
setup.py
src/__init__.py
src/__main__.py
src/apiclient.py
src/configurator.py
src/converter.py
src/importer.py
src/parser.py
src/status.py
src/testcase.py
src/../connection_config.ini
testgear_importer_junit.egg-info/PKG-INFO
testgear_importer_junit.egg-info/SOURCES.txt
testgear_importer_junit.egg-info/dependency_links.txt
testgear_importer_junit.egg-info/entry_points.txt
testgear_importer_junit.egg-info/requires.txt
testgear_importer_junit.egg-info/top_level.txt