Metadata-Version: 2.1
Name: testgear-importer-junit
Version: 1.2.4
Summary: Junit report importer for Test IT
Home-page: https://pypi.org/project/testgear-importer-junit/
Author: Integration team
Author-email: integrations@test-gear.io
License: Apache-2.0
Platform: UNKNOWN
Classifier: Programming Language :: Python :: 3
Classifier: Programming Language :: Python :: 3.6
Classifier: Programming Language :: Python :: 3.7
Classifier: Programming Language :: Python :: 3.8
Classifier: Programming Language :: Python :: 3.9
